<?xml version="1.0" encoding="utf-8"?>
<TextureAtlas imagePath="meanbfPIXEL.png">
	<!-- Created with Adobe Animate version 20.0.3.25487 -->
	<!-- http://www.adobe.com/products/animate.html -->
	<SubTexture name="BF NOTE DOWN MISS instance 10000" x="0" y="0" width="101" height="101" pivotX="50" pivotY="50"/>
	<SubTexture name="BF NOTE DOWN MISS instance 10001" x="111" y="0" width="101" height="101"/>
	<SubTexture name="BF NOTE DOWN MISS instance 10002" x="111" y="0" width="101" height="101"/>
	<SubTexture name="BF NOTE DOWN MISS instance 10003" x="222" y="0" width="101" height="101"/>
	<SubTexture name="BF NOTE DOWN MISS instance 10004" x="222" y="0" width="101" height="101"/>
	<SubTexture name="BF NOTE DOWN MISS instance 10005" x="222" y="0" width="101" height="101"/>
	<SubTexture name="BF NOTE DOWN MISS instance 10006" x="222" y="0" width="101" height="101"/>
	<SubTexture name="BF NOTE DOWN MISS instance 10007" x="222" y="0" width="101" height="101"/>
	<SubTexture name="BF NOTE DOWN MISS instance 10008" x="222" y="0" width="101" height="101"/>
	<SubTexture name="BF NOTE DOWN MISS instance 10009" x="222" y="0" width="101" height="101"/>
	<SubTexture name="BF NOTE DOWN MISS instance 10010" x="222" y="0" width="101" height="101"/>
	<SubTexture name="BF NOTE DOWN MISS instance 10011" x="222" y="0" width="101" height="101"/>
	<SubTexture name="BF NOTE DOWN MISS instance 10012" x="222" y="0" width="101" height="101"/>
	<SubTexture name="BF NOTE DOWN MISS instance 10013" x="222" y="0" width="101" height="101"/>
	<SubTexture name="BF NOTE DOWN MISS instance 10014" x="222" y="0" width="101" height="101"/>
	<SubTexture name="BF NOTE DOWN instance 10000" x="0" y="0" width="101" height="101" pivotX="50" pivotY="50"/>
	<SubTexture name="BF NOTE DOWN instance 10001" x="0" y="0" width="101" height="101"/>
	<SubTexture name="BF NOTE DOWN instance 10002" x="333" y="0" width="101" height="101"/>
	<SubTexture name="BF NOTE DOWN instance 10003" x="333" y="0" width="101" height="101"/>
	<SubTexture name="BF NOTE DOWN instance 10004" x="333" y="0" width="101" height="101"/>
	<SubTexture name="BF NOTE DOWN instance 10005" x="333" y="0" width="101" height="101"/>
	<SubTexture name="BF NOTE DOWN instance 10006" x="333" y="0" width="101" height="101"/>
	<SubTexture name="BF NOTE DOWN instance 10007" x="333" y="0" width="101" height="101"/>
	<SubTexture name="BF NOTE DOWN instance 10008" x="333" y="0" width="101" height="101"/>
	<SubTexture name="BF NOTE DOWN instance 10009" x="333" y="0" width="101" height="101"/>
	<SubTexture name="BF NOTE DOWN instance 10010" x="333" y="0" width="101" height="101"/>
	<SubTexture name="BF NOTE DOWN instance 10011" x="333" y="0" width="101" height="101"/>
	<SubTexture name="BF NOTE DOWN instance 10012" x="333" y="0" width="101" height="101"/>
	<SubTexture name="BF NOTE DOWN instance 10013" x="333" y="0" width="101" height="101"/>
	<SubTexture name="BF NOTE LEFT MISS instance 10000" x="444" y="0" width="101" height="101" pivotX="50" pivotY="50"/>
	<SubTexture name="BF NOTE LEFT MISS instance 10001" x="555" y="0" width="101" height="101"/>
	<SubTexture name="BF NOTE LEFT MISS instance 10002" x="555" y="0" width="101" height="101"/>
	<SubTexture name="BF NOTE LEFT MISS instance 10003" x="666" y="0" width="101" height="101"/>
	<SubTexture name="BF NOTE LEFT MISS instance 10004" x="666" y="0" width="101" height="101"/>
	<SubTexture name="BF NOTE LEFT MISS instance 10005" x="666" y="0" width="101" height="101"/>
	<SubTexture name="BF NOTE LEFT MISS instance 10006" x="666" y="0" width="101" height="101"/>
	<SubTexture name="BF NOTE LEFT MISS instance 10007" x="666" y="0" width="101" height="101"/>
	<SubTexture name="BF NOTE LEFT MISS instance 10008" x="666" y="0" width="101" height="101"/>
	<SubTexture name="BF NOTE LEFT MISS instance 10009" x="666" y="0" width="101" height="101"/>
	<SubTexture name="BF NOTE LEFT MISS instance 10010" x="666" y="0" width="101" height="101"/>
	<SubTexture name="BF NOTE LEFT MISS instance 10011" x="666" y="0" width="101" height="101"/>
	<SubTexture name="BF NOTE LEFT MISS instance 10012" x="666" y="0" width="101" height="101"/>
	<SubTexture name="BF NOTE LEFT MISS instance 10013" x="666" y="0" width="101" height="101"/>
	<SubTexture name="BF NOTE LEFT MISS instance 10014" x="666" y="0" width="101" height="101"/>
	<SubTexture name="BF NOTE LEFT instance 10000" x="444" y="0" width="101" height="101" pivotX="50" pivotY="50"/>
	<SubTexture name="BF NOTE LEFT instance 10001" x="444" y="0" width="101" height="101"/>
	<SubTexture name="BF NOTE LEFT instance 10002" x="777" y="0" width="101" height="101"/>
	<SubTexture name="BF NOTE LEFT instance 10003" x="777" y="0" width="101" height="101"/>
	<SubTexture name="BF NOTE LEFT instance 10004" x="777" y="0" width="101" height="101"/>
	<SubTexture name="BF NOTE LEFT instance 10005" x="777" y="0" width="101" height="101"/>
	<SubTexture name="BF NOTE LEFT instance 10006" x="777" y="0" width="101" height="101"/>
	<SubTexture name="BF NOTE LEFT instance 10007" x="777" y="0" width="101" height="101"/>
	<SubTexture name="BF NOTE LEFT instance 10008" x="777" y="0" width="101" height="101"/>
	<SubTexture name="BF NOTE LEFT instance 10009" x="777" y="0" width="101" height="101"/>
	<SubTexture name="BF NOTE LEFT instance 10010" x="777" y="0" width="101" height="101"/>
	<SubTexture name="BF NOTE LEFT instance 10011" x="777" y="0" width="101" height="101"/>
	<SubTexture name="BF NOTE LEFT instance 10012" x="777" y="0" width="101" height="101"/>
	<SubTexture name="BF NOTE LEFT instance 10013" x="777" y="0" width="101" height="101"/>
	<SubTexture name="BF NOTE RIGHT MISS instance 10000" x="888" y="0" width="101" height="101" pivotX="50" pivotY="50"/>
	<SubTexture name="BF NOTE RIGHT MISS instance 10001" x="0" y="111" width="101" height="101"/>
	<SubTexture name="BF NOTE RIGHT MISS instance 10002" x="0" y="111" width="101" height="101"/>
	<SubTexture name="BF NOTE RIGHT MISS instance 10003" x="111" y="111" width="101" height="101"/>
	<SubTexture name="BF NOTE RIGHT MISS instance 10004" x="111" y="111" width="101" height="101"/>
	<SubTexture name="BF NOTE RIGHT MISS instance 10005" x="111" y="111" width="101" height="101"/>
	<SubTexture name="BF NOTE RIGHT MISS instance 10006" x="111" y="111" width="101" height="101"/>
	<SubTexture name="BF NOTE RIGHT MISS instance 10007" x="111" y="111" width="101" height="101"/>
	<SubTexture name="BF NOTE RIGHT MISS instance 10008" x="111" y="111" width="101" height="101"/>
	<SubTexture name="BF NOTE RIGHT MISS instance 10009" x="111" y="111" width="101" height="101"/>
	<SubTexture name="BF NOTE RIGHT MISS instance 10010" x="111" y="111" width="101" height="101"/>
	<SubTexture name="BF NOTE RIGHT MISS instance 10011" x="111" y="111" width="101" height="101"/>
	<SubTexture name="BF NOTE RIGHT MISS instance 10012" x="111" y="111" width="101" height="101"/>
	<SubTexture name="BF NOTE RIGHT MISS instance 10013" x="111" y="111" width="101" height="101"/>
	<SubTexture name="BF NOTE RIGHT instance 10000" x="888" y="0" width="101" height="101" pivotX="50" pivotY="50"/>
	<SubTexture name="BF NOTE RIGHT instance 10001" x="888" y="0" width="101" height="101"/>
	<SubTexture name="BF NOTE RIGHT instance 10002" x="222" y="111" width="101" height="101"/>
	<SubTexture name="BF NOTE RIGHT instance 10003" x="222" y="111" width="101" height="101"/>
	<SubTexture name="BF NOTE RIGHT instance 10004" x="222" y="111" width="101" height="101"/>
	<SubTexture name="BF NOTE RIGHT instance 10005" x="222" y="111" width="101" height="101"/>
	<SubTexture name="BF NOTE RIGHT instance 10006" x="222" y="111" width="101" height="101"/>
	<SubTexture name="BF NOTE RIGHT instance 10007" x="222" y="111" width="101" height="101"/>
	<SubTexture name="BF NOTE RIGHT instance 10008" x="222" y="111" width="101" height="101"/>
	<SubTexture name="BF NOTE RIGHT instance 10009" x="222" y="111" width="101" height="101"/>
	<SubTexture name="BF NOTE RIGHT instance 10010" x="222" y="111" width="101" height="101"/>
	<SubTexture name="BF NOTE RIGHT instance 10011" x="222" y="111" width="101" height="101"/>
	<SubTexture name="BF NOTE RIGHT instance 10012" x="222" y="111" width="101" height="101"/>
	<SubTexture name="BF NOTE RIGHT instance 10013" x="222" y="111" width="101" height="101"/>
	<SubTexture name="BF NOTE UP MISS instance 10000" x="333" y="111" width="101" height="101" pivotX="50" pivotY="50"/>
	<SubTexture name="BF NOTE UP MISS instance 10001" x="444" y="111" width="101" height="101"/>
	<SubTexture name="BF NOTE UP MISS instance 10002" x="444" y="111" width="101" height="101"/>
	<SubTexture name="BF NOTE UP MISS instance 10003" x="555" y="111" width="101" height="101"/>
	<SubTexture name="BF NOTE UP MISS instance 10004" x="555" y="111" width="101" height="101"/>
	<SubTexture name="BF NOTE UP MISS instance 10005" x="555" y="111" width="101" height="101"/>
	<SubTexture name="BF NOTE UP MISS instance 10006" x="555" y="111" width="101" height="101"/>
	<SubTexture name="BF NOTE UP MISS instance 10007" x="555" y="111" width="101" height="101"/>
	<SubTexture name="BF NOTE UP MISS instance 10008" x="555" y="111" width="101" height="101"/>
	<SubTexture name="BF NOTE UP MISS instance 10009" x="555" y="111" width="101" height="101"/>
	<SubTexture name="BF NOTE UP MISS instance 10010" x="555" y="111" width="101" height="101"/>
	<SubTexture name="BF NOTE UP MISS instance 10011" x="555" y="111" width="101" height="101"/>
	<SubTexture name="BF NOTE UP MISS instance 10012" x="555" y="111" width="101" height="101"/>
	<SubTexture name="BF NOTE UP MISS instance 10013" x="555" y="111" width="101" height="101"/>
	<SubTexture name="BF NOTE UP MISS instance 10014" x="555" y="111" width="101" height="101"/>
	<SubTexture name="BF NOTE UP instance 10000" x="333" y="111" width="101" height="101" pivotX="50" pivotY="50"/>
	<SubTexture name="BF NOTE UP instance 10001" x="333" y="111" width="101" height="101"/>
	<SubTexture name="BF NOTE UP instance 10002" x="666" y="111" width="101" height="101"/>
	<SubTexture name="BF NOTE UP instance 10003" x="666" y="111" width="101" height="101"/>
	<SubTexture name="BF NOTE UP instance 10004" x="666" y="111" width="101" height="101"/>
	<SubTexture name="BF NOTE UP instance 10005" x="666" y="111" width="101" height="101"/>
	<SubTexture name="BF NOTE UP instance 10006" x="666" y="111" width="101" height="101"/>
	<SubTexture name="BF NOTE UP instance 10007" x="666" y="111" width="101" height="101"/>
	<SubTexture name="BF NOTE UP instance 10008" x="666" y="111" width="101" height="101"/>
	<SubTexture name="BF NOTE UP instance 10009" x="666" y="111" width="101" height="101"/>
	<SubTexture name="BF NOTE UP instance 10010" x="666" y="111" width="101" height="101"/>
	<SubTexture name="BF NOTE UP instance 10011" x="666" y="111" width="101" height="101"/>
	<SubTexture name="BF NOTE UP instance 10012" x="666" y="111" width="101" height="101"/>
	<SubTexture name="BF NOTE UP instance 10013" x="666" y="111" width="101" height="101"/>
	<SubTexture name="BF idle dance instance 10000" x="777" y="111" width="101" height="101" pivotX="50" pivotY="50"/>
	<SubTexture name="BF idle dance instance 10001" x="777" y="111" width="101" height="101"/>
	<SubTexture name="BF idle dance instance 10002" x="888" y="111" width="101" height="101"/>
	<SubTexture name="BF idle dance instance 10003" x="888" y="111" width="101" height="101"/>
	<SubTexture name="BF idle dance instance 10004" x="0" y="222" width="101" height="101"/>
	<SubTexture name="BF idle dance instance 10005" x="0" y="222" width="101" height="101"/>
	<SubTexture name="BF idle dance instance 10006" x="111" y="222" width="101" height="101"/>
	<SubTexture name="BF idle dance instance 10007" x="111" y="222" width="101" height="101"/>
	<SubTexture name="BF idle dance instance 10008" x="222" y="222" width="101" height="101"/>
	<SubTexture name="BF idle dance instance 10009" x="222" y="222" width="101" height="101"/>
	<SubTexture name="BF idle dance instance 10010" x="222" y="222" width="101" height="101"/>
	<SubTexture name="BF idle dance instance 10011" x="222" y="222" width="101" height="101"/>
	<SubTexture name="BF idle dance instance 10012" x="222" y="222" width="101" height="101"/>
	<SubTexture name="BF idle dance instance 10013" x="222" y="222" width="101" height="101"/>
</TextureAtlas>
